django_sql_sniffer/__init__.py
django_sql_sniffer/analyzer.py
django_sql_sniffer/injector.py
django_sql_sniffer/listener.py
django_sql_sniffer/sniffer.py
django_sql_sniffer-1.0.3.dist-info/LICENSE
django_sql_sniffer-1.0.3.dist-info/METADATA
django_sql_sniffer-1.0.3.dist-info/WHEEL
django_sql_sniffer-1.0.3.dist-info/entry_points.txt
django_sql_sniffer-1.0.3.dist-info/top_level.txt
django_sql_sniffer-1.0.3.dist-info/RECORD
