Metadata-Version: 2.1
Name: django-sql-sniffer
Version: 1.0.3
Summary: Django SQL Sniffer
Home-page: https://github.com/gruuya/django-sql-sniffer
Author: Marko Grujic
Author-email: markoog@gmail.com
License: MIT
Keywords: django sql query remote process analysis
Platform: UNKNOWN
Requires-Python: >=3.5
Requires-Dist: django
